svo_cpp/svo_cpp.cpython-312-x86_64-linux-gnu.so
svo_cpp/libfast.so
svo_cpp/_version.py
svo_cpp/libvikit_common.so
svo_cpp/__init__.py
svo_cpp-1.5.0.dist-info/RECORD
svo_cpp-1.5.0.dist-info/METADATA
svo_cpp-1.5.0.dist-info/top_level.txt
svo_cpp-1.5.0.dist-info/WHEEL
svo_cpp-1.5.0.dist-info/licenses/LICENSE
svo_cpp.libs/libopencv_img_hash-8bb80183.so.4.8.0
svo_cpp.libs/libboost_system-69a6c43e.so.1.66.0
svo_cpp.libs/libopencv_stitching-434d6780.so.4.8.0
svo_cpp.libs/libopencv_rgbd-47d73dd5.so.4.8.0
svo_cpp.libs/libboost_thread-473b539f.so.1.66.0
svo_cpp.libs/libopencv_tracking-87bce953.so.4.8.0
svo_cpp.libs/libopencv_xobjdetect-6cee095f.so.4.8.0
svo_cpp.libs/libopencv_bgsegm-28684f10.so.4.8.0
svo_cpp.libs/libopencv_superres-6f0fe9af.so.4.8.0
svo_cpp.libs/libopencv_reg-e6fb310b.so.4.8.0
svo_cpp.libs/libopencv_quality-2cb08c6e.so.4.8.0
svo_cpp.libs/libopencv_wechat_qrcode-adb2d214.so.4.8.0
svo_cpp.libs/libopencv_aruco-070ed9dd.so.4.8.0
svo_cpp.libs/libopencv_shape-047e6df2.so.4.8.0
svo_cpp.libs/libopencv_alphamat-12b36c62.so.4.8.0
svo_cpp.libs/libopencv_fuzzy-fdf42fba.so.4.8.0
svo_cpp.libs/libboost_chrono-67089fad.so.1.66.0
svo_cpp.libs/libopencv_saliency-9198bb6f.so.4.8.0
svo_cpp.libs/libopencv_dnn_superres-e9decf7e.so.4.8.0
svo_cpp.libs/libopencv_line_descriptor-31f73c02.so.4.8.0
svo_cpp.libs/libopencv_dnn_objdetect-c87572b5.so.4.8.0
svo_cpp.libs/libjbig-2504a0c3.so.2.1
svo_cpp.libs/libopencv_surface_matching-691403ef.so.4.8.0
svo_cpp.libs/libopencv_xphoto-4089899a.so.4.8.0
svo_cpp.libs/libvikit_common-ed9ee7de.so
svo_cpp.libs/libopencv_dnn-8c6fd9c7.so.4.8.0
svo_cpp.libs/libopencv_face-63fd1d97.so.4.8.0
svo_cpp.libs/libopencv_bioinspired-73436b9e.so.4.8.0
svo_cpp.libs/libopencv_stereo-c8e337ea.so.4.8.0
svo_cpp.libs/libpng16-748299c7.so.16.34.0
svo_cpp.libs/libopencv_xfeatures2d-7dff2403.so.4.8.0
svo_cpp.libs/libopencv_dpm-ad1a19a0.so.4.8.0
svo_cpp.libs/libopencv_text-a898620d.so.4.8.0
svo_cpp.libs/libopencv_phase_unwrapping-ba61d35d.so.4.8.0
svo_cpp.libs/libjpeg-e87d2658.so.62.2.0
svo_cpp.libs/libopencv_plot-c5729913.so.4.8.0
svo_cpp.libs/libtbb-f09e8534.so.2
