Metadata-Version: 2.4
Name: svo_cpp
Version: 1.5.0
Summary: Semi Direct Visual Odometry with python bindings
Maintainer-email: "Alex S." <savaalexandru562@gmail.com>
License:                     GNU GENERAL PUBLIC LICENSE
Project-URL: Bug Tracker, https://github.com/AlexandruRO45/rpg_svo/issues
Project-URL: Source, https://github.com/AlexandruRO45/rpg_svo/
Project-URL: Documentation, https://github.com/AlexandruRO45/rpg_svo/
Classifier: Intended Audience :: Developers
Classifier: License :: OSI Approved :: GNU General Public License v3 or later (GPLv3+)
Classifier: Programming Language :: C++
Classifier: Programming Language :: Python :: 3
Classifier: Programming Language :: Python :: 3 :: Only
Classifier: Programming Language :: Python :: 3.8
Classifier: Programming Language :: Python :: 3.9
Classifier: Programming Language :: Python :: 3.10
Classifier: Programming Language :: Python :: 3.11
Classifier: Programming Language :: Python :: 3.12
Classifier: Operating System :: POSIX :: Linux
Classifier: Topic :: Scientific/Engineering :: Image Processing
Classifier: Topic :: Software Development :: Libraries :: Python Modules
Requires-Python: >=3.8
License-File: LICENSE
Requires-Dist: numpy>=1.19.0
Requires-Dist: opencv-python>=4.5.0
Provides-Extra: test
Requires-Dist: pytest>=6.0; extra == "test"
Requires-Dist: pyyaml>=5.4; extra == "test"
Provides-Extra: dev
Requires-Dist: pytest>=6.0; extra == "dev"
Requires-Dist: pyyaml>=5.4; extra == "dev"
Requires-Dist: build; extra == "dev"
Requires-Dist: twine; extra == "dev"
Dynamic: license-file
